Workbook

Sheet Assumptions
A1: PymeWebPro · Client Cost & Revenue Model
A2: All amounts in Colombian pesos (COP). Blue cells = editable inputs. Black cells = formulas. Green cells = cross-sheet references.
A4: LLM API PRICING (COP per 1M tokens)
A5: Anthropic Claude Sonnet 4.6 · input | B5: 12000 | C5: Edit if Anthropic pricing or TRM changes
A6: Anthropic Claude Sonnet 4.6 · output | B6: 60000 | C6: Edit if Anthropic pricing or TRM changes
A7: Gemini 2.0 Flash · input | B7: 400 | C7: Optional · much cheaper for classification or summarization
A8: Gemini 2.0 Flash · output | B8: 1600 | C8: Optional
A10: CHAT AGENT · token usage per conversation (Pro clients · site-aware)
A11: Input tokens / conv | B11: 40000 | C11: Site-aware = fetch_page tool returns chunks of client's site content · higher token count
A12: Output tokens / conv | B12: 3000
A13: % offload to Gemini | B13: 0 | C13: Set 30-60% to cut API cost · use Gemini for classification + content extraction
A15: DERIVED PER-CONVERSATION API COST (Pro clients)
A16: Anthropic cost / conv | B16: =(B11*(1-B13)*B5+B12*(1-B13)*B6)/1000000 -> 660
A17: Gemini cost / conv | B17: =(B11*B13*B7+B12*B13*B8)/1000000 -> 0
A18: Total cost / conv | B18: =B16+B17 -> 660
A20: VOLUME SCENARIOS (conversations / month · Pro clients only)
A21: Light (~1 conv/day) | B21: 30
A22: Medium (~3 conv/day) | B22: 100
A23: Heavy (~10 conv/day) | B23: 300
A24: Power (~26 conv/day) | B24: 800
A26: WOMPI (payment processor)
A27: Wompi · percentage fee | B27: 0.0299 | C27: 2.99% of charged amount
A28: Wompi · fixed per transaction (COP) | B28: 2800 | C28: $2.800 COP per approved transaction

Sheet Plans
A1: Plans · what each client pays
A2: Edit blue cells to test pricing. The chat agent is bundled into Pro (not available on Essential).
A4: Plan | B4: Plan price (one-time, COP) | C4: Included period | D4: Monthly bundle after included (COP) | E4: Annual prepay (COP) | F4: Notes
A5: Essential | B5: 390000 | C5: 1 month | D5: 20000 | E5: 200000 | F5: Bare website. Hosting + support only. No chat agent. Monthly bundle is just hosting + support.
A6: Pro | B6: 690000 | C6: 1 year | D6: 100000 | E6: 1000000 | F6: Premium tier. Includes site-aware chat agent + hosting + support, all bundled. After the included year: $100.000 COP/mo OR $1.000.000 COP/yr prepay (2 months free).

Sheet Per-Client Cost
A1: Per-client cost · what each new client costs you in cash
A2: All cash out, no labor. Cloudflare, D1, KV sit in free tier · $0. The only cost line is Anthropic API (Pro only · Essential clients have no chat agent).
A4: Plan | B4: Volume | C4: Conv / month | D4: Anthropic cost / conv | E4: API cost / month | F4: Cloudflare / month | G4: Wompi fee on monthly recurring | H4: Total cash cost / month
A5: Essential | B5: N/A | C5: 0 | D5: - | E5: 0 | F5: 0 | G5: =Plans!D5*Assumptions!B27+Assumptions!B28 -> 3398 | H5: =E5+F5+G5 -> 3398
A7: Pro | B7: Light | C7: =Assumptions!B21 -> 30 | D7: =Assumptions!B18 -> 660 | E7: =C7*D7 -> 19800 | F7: 0 | G7: =Plans!D6*Assumptions!B27+Assumptions!B28 -> 5790 | H7: =E7+F7+G7 -> 25590
A8: Pro | B8: Medium | C8: =Assumptions!B22 -> 100 | D8: =Assumptions!B18 -> 660 | E8: =C8*D8 -> 66000 | F8: 0 | G8: =Plans!D6*Assumptions!B27+Assumptions!B28 -> 5790 | H8: =E8+F8+G8 -> 71790
A9: Pro | B9: Heavy | C9: =Assumptions!B23 -> 300 | D9: =Assumptions!B18 -> 660 | E9: =C9*D9 -> 198000 | F9: 0 | G9: =Plans!D6*Assumptions!B27+Assumptions!B28 -> 5790 | H9: =E9+F9+G9 -> 203790
A10: Pro | B10: Power | C10: =Assumptions!B24 -> 800 | D10: =Assumptions!B18 -> 660 | E10: =C10*D10 -> 528000 | F10: 0 | G10: =Plans!D6*Assumptions!B27+Assumptions!B28 -> 5790 | H10: =E10+F10+G10 -> 533790
A12: Notes:
A13: · Essential clients have no chat agent, so API cost is $0. Their only running cost is hosting which Cloudflare provides free.
A14: · Pro clients run the chat agent. Cash cost = Anthropic API per conversation. Cloudflare/D1/KV stay free at this scale.
A15: · Wompi fee shown is the fee on the $20.000 COP monthly hosting charge once the included period ends. The one-time plan-price payment also has a Wompi fee · see the Per-Client Revenue tab.

Sheet Per-Client Revenue
A1: Per-client revenue · year 1 vs year 2+
A2: Year 1 includes the one-time plan payment + any out-of-included-period hosting charges. Year 2+ is steady-state recurring hosting only.
A4: Plan | B4: Year | C4: Plan price collected | D4: Hosting months charged | E4: Hosting revenue | F4: Wompi fees (total) | G4: Net revenue received
A5: Essential | B5: Year 1 | C5: =Plans!B5 -> 390000 | D5: 11 | E5: =D5*Plans!D5 -> 220000 | F5: =(Plans!B5*Assumptions!B27+Assumptions!B28)+D5*(Plans!D5*Assumptions!B27+Assumptions!B28) -> 51839 | G5: =C5+E5-F5 -> 558161
A6: Essential | B6: Year 2+ | C6: 0 | D6: 12 | E6: =D6*Plans!D5 -> 240000 | F6: =D6*(Plans!D5*Assumptions!B27+Assumptions!B28) -> 40776 | G6: =C6+E6-F6 -> 199224
A8: Pro | B8: Year 1 | C8: =Plans!B6 -> 690000 | D8: 0 | E8: =D8*Plans!D6 -> 0 | F8: =(Plans!B6*Assumptions!B27+Assumptions!B28)+D8*(Plans!D6*Assumptions!B27+Assumptions!B28) -> 23431 | G8: =C8+E8-F8 -> 666569
A9: Pro | B9: Year 2+ | C9: 0 | D9: 12 | E9: =D9*Plans!D6 -> 1200000 | F9: =D9*(Plans!D6*Assumptions!B27+Assumptions!B28) -> 69480 | G9: =C9+E9-F9 -> 1130520

Sheet Portfolio Model
A1: Portfolio model · whole business at N clients
A2: Enter # clients per plan × volume. Sheet computes monthly recurring economics in steady state (year 2+: clients pay only hosting).
A4: ESSENTIAL CLIENTS
A5: # Essential clients | B5: 10
A7: PRO CLIENTS (by volume)
B8: Light | C8: Medium | D8: Heavy | E8: Power | F8: Total
A9: # Pro clients | B9: 3 | C9: 4 | D9: 1 | E9: 0 | F9: =SUM(B9:E9) -> 8
A12: STEADY-STATE MONTHLY RECURRING (Year 2+)
A13: Essential clients
A14: Monthly hosting revenue | B14: =B5*Plans!D5 -> 200000
A15: (−) Wompi fees on hosting | B15: =-B5*(Plans!D5*Assumptions!B27+Assumptions!B28) -> -33980
A16: (=) Net Essential revenue / month | B16: =B14+B15 -> 166020
A18: Pro clients
A19: # Pro clients | B19: =F9 -> 8
A20: Total Pro conversations / month | B20: =B9*Assumptions!B21+C9*Assumptions!B22+D9*Assumptions!B23+E9*Assumptions!B24 -> 790
A21: Monthly bundle revenue (hosting + support + chat) | B21: =F9*Plans!D6 -> 800000
A22: (−) Anthropic API cost | B22: =-B20*Assumptions!B18 -> -521400
A23: (−) Wompi fees on bundle | B23: =-F9*(Plans!D6*Assumptions!B27+Assumptions!B28) -> -46320
A24: (=) Net Pro revenue / month | B24: =B21+B22+B23 -> 232280
A26: TOTAL net recurring / month (Year 2+ steady state) | B26: =B16+B24 -> 398300
A27: TOTAL net recurring / year (Year 2+) | B27: =B26*12 -> 4779600
A29: YEAR-1 ONE-TIME SIGN-UP REVENUE (if all current clients are new in this year)
A30: Essential sign-up revenue | B30: =B5*Plans!B5 -> 3900000
A31: (−) Wompi fees on Essential sign-ups | B31: =-B5*(Plans!B5*Assumptions!B27+Assumptions!B28) -> -144610
A32: Pro sign-up revenue | B32: =F9*Plans!B6 -> 5520000
A33: (−) Wompi fees on Pro sign-ups | B33: =-F9*(Plans!B6*Assumptions!B27+Assumptions!B28) -> -187448
A34: Total one-time net (year 1 only) | B34: =SUM(B30:B33) -> 9087942

Sheet Read me
A1: How to use this model
A3: Color conventions:
A4: · BLUE cells with pale yellow background = editable inputs. Change these to test scenarios.
A5: · BLACK cells = local formulas within the sheet.
A6: · GREEN cells = references to another sheet in the same workbook.
A8: Sheets:
A10: 1. Assumptions · Anthropic and Gemini API pricing (COP per 1M tokens), site-aware chat agent token usage per conversation (Pro clients only), the 'percent offloaded to Gemini' lever (cost optimization), conversation volume scenarios, Wompi merchant fees.
A12: 2. Plans · The two plans. Essential = $390.000 COP one-time, 1 month hosting included. Pro = $690.000 COP one-time, 1 year hosting + site-aware chat agent included. After the included hosting period, $20.000 COP/month. Chat agent stays bundled · no separate recurring chat fee in the current model.
A14: 3. Per-Client Cost · Cash cost per client, per month. Essential clients cost you nothing recurring beyond Wompi on hosting. Pro clients cost you Anthropic API by conversation volume, plus the Wompi cut on the hosting charge.
A16: 4. Per-Client Revenue · Year-1 vs Year-2+ economics per client. Year 1: plan price + partial hosting (Essential only). Year 2+: just 12 months of hosting.
A18: 5. Portfolio Model · Enter # of Essential clients and # of Pro clients (split by conversation volume). Steady-state monthly recurring net revenue, annual rollup, and the one-time sign-up revenue if these clients are all new in the current year.
A20: Levers worth knowing:
... A28: · If recurring net needs to be positive: bump the monthly Pro fee, cap conversations per month, or add a separate chat agent fee for year 2+ (e.g. $100.000 COP/mo as you mentioned). Easy to model · just raise the Pro 'Monthly hosting after included' value on the Plans sheet, or add a separate input.
