Workbook

Sheet Assumptions
A1: PymeWebPro · Financial Plan · Assumptions
A2: All amounts in COP. Yellow cells are editable inputs.
A4: Sales volume
A5: Page sales per month (units) | B5: 4 | C5: Base assumption from user
A6: Attach rate on Plan de ventas | B6: 1 | C6: 100% take MRR; change to model upsell rate
A7: Monthly churn (active customers) | B7: 0 | C7: Set to 0 for base case; raise for cancellations
A8: Pricing (IVA included, customer-facing)
A9: Page price one-time | B9: 400000 | C9: Includes Ficha de Google Business
A10: Plan de ventas MRR | B10: 150000 | C10: Chatbot + catalog + monthly report
A11: IVA rate | B11: 0.19 | C11: Colombia VAT, pass-through to DIAN
A12: Sales commissions (paid to contractor)
A13: One-time on page sale | B13: 0.2 | C13: Per contract clause 4
A14: Recurring on MRR | B14: 0.1 | C14: Per contract clause 4
A15: Recurring duration (months) | B15: 12 | C15: Cap on recurring commission per customer
A16: Retefuente withheld (info only) | B16: 0.1 | C16: Withheld from commission, remitted to DIAN, neutral to NSC
A17: Wompi payment processing
A18: Wompi % per transaction | B18: 0.0299 | C18: Card rate; PSE is ~1.79%
A19: Wompi flat fee per transaction (COP) | B19: 900 | C19: Per transaction, before IVA
A20: IVA on Wompi fees | B20: 0.19 | C20: Wompi charges 19% IVA on its fee
A21: Colombian taxes (company side)
A22: ICA Medellín (services) | B22: 0.007 | C22: ~7 per thousand on services revenue
A23: Corporate income tax (renta) | B23: 0.35 | C23: Annual; applied to monthly operating profit here
A24: Fixed monthly infrastructure
A25: Cloudflare Workers paid plan | B25: 20000 | C25: $5 USD at ~$4.000/USD
A26: Anthropic API (Valentina agent) | B26: 160000 | C26: Estimate at low volume, prompt-cached
A27: Gemini API (history compression) | B27: 20000 | C27: Cheap compression model
A28: Resend (transactional email) | B28: 80000 | C28: $20 USD
A29: Domain renewals (amortized) | B29: 5000 | C29: pymewebpro.com + subdomains
A30: D1 / Pages / KV | B30: 0 | C30: Free tiers cover current volume
A31: Fixed monthly admin
A32: Contador (accounting, allocated to PWP) | B32: 400000 | C32: Shared with NSC umbrella; allocate portion
A33: Cámara de Comercio renewal (amortized) | B33: 25000 | C33: ~$300k annual / 12
A34: Bank fees, miscellaneous | B34: 30000 | C34: Buffer for misc admin

Sheet Monthly P&L
A1: PymeWebPro · 24-Month Operating Plan (COP)
A3: Line item | B3: M1 | C3: M2 | D3: M3 | E3: M4 | F3: M5 | G3: M6 | H3: M7 | I3: M8 | J3: M9 | K3: M10 | L3: M11 | M3: M12 | N3: M13 | O3: M14 | P3: M15 | Q3: M16 | R3: M17 | S3: M18 | T3: M19 | U3: M20 | V3: M21 | W3: M22 | X3: M23 | Y3: M24
A5: New page sales (units) | B5: =Assumptions!$B$5 -> 4 | C5: =Assumptions!$B$5 -> 4 | D5: =Assumptions!$B$5 -> 4 | E5: =Assumptions!$B$5 -> 4 | F5: =Assumptions!$B$5 -> 4 | G5: =Assumptions!$B$5 -> 4 | H5: =Assumptions!$B$5 -> 4 | I5: =Assumptions!$B$5 -> 4 | ... Y5: =Assumptions!$B$5 -> 4
A6: New MRR customers (units) | B6: =B5*Assumptions!$B$6 -> 4 | C6: =C5*Assumptions!$B$6 -> 4 | D6: =D5*Assumptions!$B$6 -> 4 | E6: =E5*Assumptions!$B$6 -> 4 | F6: =F5*Assumptions!$B$6 -> 4 | G6: =G5*Assumptions!$B$6 -> 4 | H6: =H5*Assumptions!$B$6 -> 4 | I6: =I5*Assumptions!$B$6 -> 4 | ... Y6: =Y5*Assumptions!$B$6 -> 4
A7: Active MRR customers (cumulative) | B7: =B6 -> 4 | C7: =B7*(1-Assumptions!$B$7)+C6 -> 8 | D7: =C7*(1-Assumptions!$B$7)+D6 -> 12 | E7: =D7*(1-Assumptions!$B$7)+E6 -> 16 | F7: =E7*(1-Assumptions!$B$7)+F6 -> 20 | G7: =F7*(1-Assumptions!$B$7)+G6 -> 24 | H7: =G7*(1-Assumptions!$B$7)+H6 -> 28 | I7: =H7*(1-Assumptions!$B$7)+I6 -> 32 | J7: =I7*(1-Assumptions!$B$7)+J6 -> 36 | ... Y7: =X7*(1-Assumptions!$B$7)+Y6 -> 96
A8: Customers in commission window (last 12mo) | B8: =B7 -> 4 | C8: =C7 -> 8 | D8: =D7 -> 12 | E8: =E7 -> 16 | F8: =F7 -> 20 | G8: =G7 -> 24 | H8: =H7 -> 28 | I8: =I7 -> 32 | ... M8: =M7 -> 48 | N8: =SUM(C6:N6) -> 48 | O8: =SUM(D6:O6) -> 48 | P8: =SUM(E6:P6) -> 48 | Q8: =SUM(F6:Q6) -> 48 | R8: =SUM(G6:R6) -> 48 | S8: =SUM(H6:S6) -> 48 | T8: =SUM(I6:T6) -> 48 | U8: =SUM(J6:U6) -> 48 | ... Y8: =SUM(N6:Y6) -> 48
A10: REVENUE (IVA included)
A11: Page revenue (gross) | B11: =B5*Assumptions!$B$9 -> 1600000 | C11: =C5*Assumptions!$B$9 -> 1600000 | D11: =D5*Assumptions!$B$9 -> 1600000 | E11: =E5*Assumptions!$B$9 -> 1600000 | F11: =F5*Assumptions!$B$9 -> 1600000 | G11: =G5*Assumptions!$B$9 -> 1600000 | H11: =H5*Assumptions!$B$9 -> 1600000 | I11: =I5*Assumptions!$B$9 -> 1600000 | ... Y11: =Y5*Assumptions!$B$9 -> 1600000
A12: MRR revenue (gross) | B12: =B7*Assumptions!$B$10 -> 600000 | C12: =C7*Assumptions!$B$10 -> 1200000 | D12: =D7*Assumptions!$B$10 -> 1800000 | E12: =E7*Assumptions!$B$10 -> 2400000 | F12: =F7*Assumptions!$B$10 -> 3000000 | G12: =G7*Assumptions!$B$10 -> 3600000 | H12: =H7*Assumptions!$B$10 -> 4200000 | I12: =I7*Assumptions!$B$10 -> 4800000 | ... Y12: =Y7*Assumptions!$B$10 -> 14400000
A13: Total gross revenue | B13: =B11+B12 -> 2200000 | C13: =C11+C12 -> 2800000 | D13: =D11+D12 -> 3400000 | E13: =E11+E12 -> 4000000 | F13: =F11+F12 -> 4600000 | G13: =G11+G12 -> 5200000 | H13: =H11+H12 -> 5800000 | I13: =I11+I12 -> 6400000 | ... Y13: =Y11+Y12 -> 16000000
A14: Less: IVA payable to DIAN | B14: =-B13*Assumptions!$B$11/(1+Assumptions!$B$11) -> -351260.5 | C14: =-C13*Assumptions!$B$11/(1+Assumptions!$B$11) -> -447058.82 | D14: =-D13*Assumptions!$B$11/(1+Assumptions!$B$11) -> -542857.14 | E14: =-E13*Assumptions!$B$11/(1+Assumptions!$B$11) -> -638655.46 | F14: =-F13*Assumptions!$B$11/(1+Assumptions!$B$11) -> -734453.78 | G14: =-G13*Assumptions!$B$11/(1+Assumptions!$B$11) -> -830252.1 | H14: =-H13*Assumptions!$B$11/(1+Assumptions!$B$11) -> -926050.42 | I14: =-I13*Assumptions!$B$11/(1+Assumptions!$B$11) -> -1021848.7 | ... Y14: =-Y13*Assumptions!$B$11/(1+Assumptions!$B$11) -> -2554621.8
A15: Net revenue (ex-IVA) | B15: =B13+B14 -> 1848739.5 | C15: =C13+C14 -> 2352941.2 | D15: =D13+D14 -> 2857142.9 | E15: =E13+E14 -> 3361344.5 | F15: =F13+F14 -> 3865546.2 | G15: =G13+G14 -> 4369747.9 | H15: =H13+H14 -> 4873949.6 | I15: =I13+I14 -> 5378151.3 | ... Y15: =Y13+Y14 -> 13445378
A17: VARIABLE COSTS
A18: Seller commission · one-time (20% × page) | B18: =-B11*Assumptions!$B$13 -> -320000 | C18: =-C11*Assumptions!$B$13 -> -320000 | D18: =-D11*Assumptions!$B$13 -> -320000 | E18: =-E11*Assumptions!$B$13 -> -320000 | F18: =-F11*Assumptions!$B$13 -> -320000 | G18: =-G11*Assumptions!$B$13 -> -320000 | H18: =-H11*Assumptions!$B$13 -> -320000 | I18: =-I11*Assumptions!$B$13 -> -320000 | ... Y18: =-Y11*Assumptions!$B$13 -> -320000
A19: Seller commission · recurring (10% × MRR, 12mo) | B19: =-B8*Assumptions!$B$10*Assumptions!$B$14 -> -60000 | C19: =-C8*Assumptions!$B$10*Assumptions!$B$14 -> -120000 | D19: =-D8*Assumptions!$B$10*Assumptions!$B$14 -> -180000 | E19: =-E8*Assumptions!$B$10*Assumptions!$B$14 -> -240000 | F19: =-F8*Assumptions!$B$10*Assumptions!$B$14 -> -300000 | G19: =-G8*Assumptions!$B$10*Assumptions!$B$14 -> -360000 | H19: =-H8*Assumptions!$B$10*Assumptions!$B$14 -> -420000 | I19: =-I8*Assumptions!$B$10*Assumptions!$B$14 -> -480000 | ... Y19: =-Y8*Assumptions!$B$10*Assumptions!$B$14 -> -720000
A20: Wompi · page transactions | B20: =-B5*(Assumptions!$B$9*Assumptions!$B$18+Assumptions!$B$19)*(1+Assumptions!$B$20) -> -61213.6 | C20: =-C5*(Assumptions!$B$9*Assumptions!$B$18+Assumptions!$B$19)*(1+Assumptions!$B$20) -> -61213.6 | D20: =-D5*(Assumptions!$B$9*Assumptions!$B$18+Assumptions!$B$19)*(1+Assumptions!$B$20) -> -61213.6 | E20: =-E5*(Assumptions!$B$9*Assumptions!$B$18+Assumptions!$B$19)*(1+Assumptions!$B$20) -> -61213.6 | F20: =-F5*(Assumptions!$B$9*Assumptions!$B$18+Assumptions!$B$19)*(1+Assumptions!$B$20) -> -61213.6 | G20: =-G5*(Assumptions!$B$9*Assumptions!$B$18+Assumptions!$B$19)*(1+Assumptions!$B$20) -> -61213.6 | H20: =-H5*(Assumptions!$B$9*Assumptions!$B$18+Assumptions!$B$19)*(1+Assumptions!$B$20) -> -61213.6 | I20: =-I5*(Assumptions!$B$9*Assumptions!$B$18+Assumptions!$B$19)*(1+Assumptions!$B$20) -> -61213.6 | ... Y20: =-Y5*(Assumptions!$B$9*Assumptions!$B$18+Assumptions!$B$19)*(1+Assumptions!$B$20) -> -61213.6
A21: Wompi · MRR transactions | B21: =-B7*(Assumptions!$B$10*Assumptions!$B$18+Assumptions!$B$19)*(1+Assumptions!$B$20) -> -25632.6 | C21: =-C7*(Assumptions!$B$10*Assumptions!$B$18+Assumptions!$B$19)*(1+Assumptions!$B$20) -> -51265.2 | D21: =-D7*(Assumptions!$B$10*Assumptions!$B$18+Assumptions!$B$19)*(1+Assumptions!$B$20) -> -76897.8 | E21: =-E7*(Assumptions!$B$10*Assumptions!$B$18+Assumptions!$B$19)*(1+Assumptions!$B$20) -> -102530.4 | F21: =-F7*(Assumptions!$B$10*Assumptions!$B$18+Assumptions!$B$19)*(1+Assumptions!$B$20) -> -128163 | G21: =-G7*(Assumptions!$B$10*Assumptions!$B$18+Assumptions!$B$19)*(1+Assumptions!$B$20) -> -153795.6 | H21: =-H7*(Assumptions!$B$10*Assumptions!$B$18+Assumptions!$B$19)*(1+Assumptions!$B$20) -> -179428.2 | I21: =-I7*(Assumptions!$B$10*Assumptions!$B$18+Assumptions!$B$19)*(1+Assumptions!$B$20) -> -205060.8 | ... Y21: =-Y7*(Assumptions!$B$10*Assumptions!$B$18+Assumptions!$B$19)*(1+Assumptions!$B$20) -> -615182.4
A22: ICA Medellín on net revenue | B22: =-B15*Assumptions!$B$22 -> -12941.176 | C22: =-C15*Assumptions!$B$22 -> -16470.588 | D22: =-D15*Assumptions!$B$22 -> -20000 | E22: =-E15*Assumptions!$B$22 -> -23529.412 | F22: =-F15*Assumptions!$B$22 -> -27058.824 | G22: =-G15*Assumptions!$B$22 -> -30588.235 | H22: =-H15*Assumptions!$B$22 -> -34117.647 | I22: =-I15*Assumptions!$B$22 -> -37647.059 | ... Y22: =-Y15*Assumptions!$B$22 -> -94117.647
A23: Total variable costs | B23: =SUM(B18:B22) -> -479787.38 | C23: =SUM(C18:C22) -> -568949.39 | D23: =SUM(D18:D22) -> -658111.4 | E23: =SUM(E18:E22) -> -747273.41 | F23: =SUM(F18:F22) -> -836435.42 | G23: =SUM(G18:G22) -> -925597.44 | H23: =SUM(H18:H22) -> -1014759.4 | I23: =SUM(I18:I22) -> -1103921.5 | ... Y23: =SUM(Y18:Y22) -> -1810513.6
A25: Gross profit | B25: =B15+B23 -> 1368952.1 | C25: =C15+C23 -> 1783991.8 | D25: =D15+D23 -> 2199031.5 | E25: =E15+E23 -> 2614071.1 | F25: =F15+F23 -> 3029110.8 | G25: =G15+G23 -> 3444150.5 | H25: =H15+H23 -> 3859190.1 | I25: =I15+I23 -> 4274229.8 | ... Y25: =Y15+Y23 -> 11634865
A26: Gross margin % | B26: =IFERROR(B25/B15,0) -> 0.74047865 | C26: =IFERROR(C25/C15,0) -> 0.75819651 | D26: =IFERROR(D25/D15,0) -> 0.76966101 | E26: =IFERROR(E25/E15,0) -> 0.77768616 | F26: =IFERROR(F25/F15,0) -> 0.78361779 | G26: =IFERROR(G25/G15,0) -> 0.78818059 | H26: =IFERROR(H25/H15,0) -> 0.79179935 | I26: =IFERROR(I25/I15,0) -> 0.7947396 | ... Y26: =IFERROR(Y25/Y15,0) -> 0.86534305
A28: FIXED COSTS (monthly)
A29: Cloudflare Workers | B29: =-Assumptions!$B$25 -> -20000 | C29: =-Assumptions!$B$25 -> -20000 | D29: =-Assumptions!$B$25 -> -20000 | E29: =-Assumptions!$B$25 -> -20000 | F29: =-Assumptions!$B$25 -> -20000 | G29: =-Assumptions!$B$25 -> -20000 | H29: =-Assumptions!$B$25 -> -20000 | I29: =-Assumptions!$B$25 -> -20000 | ... Y29: =-Assumptions!$B$25 -> -20000
A30: Anthropic API (Valentina) | B30: =-Assumptions!$B$26 -> -160000 | C30: =-Assumptions!$B$26 -> -160000 | D30: =-Assumptions!$B$26 -> -160000 | E30: =-Assumptions!$B$26 -> -160000 | F30: =-Assumptions!$B$26 -> -160000 | G30: =-Assumptions!$B$26 -> -160000 | H30: =-Assumptions!$B$26 -> -160000 | I30: =-Assumptions!$B$26 -> -160000 | ... Y30: =-Assumptions!$B$26 -> -160000
A31: Gemini API | B31: =-Assumptions!$B$27 -> -20000 | C31: =-Assumptions!$B$27 -> -20000 | D31: =-Assumptions!$B$27 -> -20000 | E31: =-Assumptions!$B$27 -> -20000 | F31: =-Assumptions!$B$27 -> -20000 | G31: =-Assumptions!$B$27 -> -20000 | H31: =-Assumptions!$B$27 -> -20000 | I31: =-Assumptions!$B$27 -> -20000 | ... Y31: =-Assumptions!$B$27 -> -20000
A32: Resend (email) | B32: =-Assumptions!$B$28 -> -80000 | C32: =-Assumptions!$B$28 -> -80000 | D32: =-Assumptions!$B$28 -> -80000 | E32: =-Assumptions!$B$28 -> -80000 | F32: =-Assumptions!$B$28 -> -80000 | G32: =-Assumptions!$B$28 -> -80000 | H32: =-Assumptions!$B$28 -> -80000 | I32: =-Assumptions!$B$28 -> -80000 | ... Y32: =-Assumptions!$B$28 -> -80000
A33: Domains | B33: =-Assumptions!$B$29 -> -5000 | C33: =-Assumptions!$B$29 -> -5000 | D33: =-Assumptions!$B$29 -> -5000 | E33: =-Assumptions!$B$29 -> -5000 | F33: =-Assumptions!$B$29 -> -5000 | G33: =-Assumptions!$B$29 -> -5000 | H33: =-Assumptions!$B$29 -> -5000 | I33: =-Assumptions!$B$29 -> -5000 | ... Y33: =-Assumptions!$B$29 -> -5000
A34: Contador (accounting) | B34: =-Assumptions!$B$32 -> -400000 | C34: =-Assumptions!$B$32 -> -400000 | D34: =-Assumptions!$B$32 -> -400000 | E34: =-Assumptions!$B$32 -> -400000 | F34: =-Assumptions!$B$32 -> -400000 | G34: =-Assumptions!$B$32 -> -400000 | H34: =-Assumptions!$B$32 -> -400000 | I34: =-Assumptions!$B$32 -> -400000 | ... Y34: =-Assumptions!$B$32 -> -400000
A35: Cámara de Comercio (amortized) | B35: =-Assumptions!$B$33 -> -25000 | C35: =-Assumptions!$B$33 -> -25000 | D35: =-Assumptions!$B$33 -> -25000 | E35: =-Assumptions!$B$33 -> -25000 | F35: =-Assumptions!$B$33 -> -25000 | G35: =-Assumptions!$B$33 -> -25000 | H35: =-Assumptions!$B$33 -> -25000 | I35: =-Assumptions!$B$33 -> -25000 | ... Y35: =-Assumptions!$B$33 -> -25000
A36: Bank fees / miscellaneous | B36: =-Assumptions!$B$34 -> -30000 | C36: =-Assumptions!$B$34 -> -30000 | D36: =-Assumptions!$B$34 -> -30000 | E36: =-Assumptions!$B$34 -> -30000 | F36: =-Assumptions!$B$34 -> -30000 | G36: =-Assumptions!$B$34 -> -30000 | H36: =-Assumptions!$B$34 -> -30000 | I36: =-Assumptions!$B$34 -> -30000 | ... Y36: =-Assumptions!$B$34 -> -30000
A37: Total fixed costs | B37: =SUM(B29:B36) -> -740000 | C37: =SUM(C29:C36) -> -740000 | D37: =SUM(D29:D36) -> -740000 | E37: =SUM(E29:E36) -> -740000 | F37: =SUM(F29:F36) -> -740000 | G37: =SUM(G29:G36) -> -740000 | H37: =SUM(H29:H36) -> -740000 | I37: =SUM(I29:I36) -> -740000 | ... Y37: =SUM(Y29:Y36) -> -740000
A39: Operating profit (pre-tax) | B39: =B25+B37 -> 628952.12 | C39: =C25+C37 -> 1043991.8 | D39: =D25+D37 -> 1459031.5 | E39: =E25+E37 -> 1874071.1 | F39: =F25+F37 -> 2289110.8 | G39: =G25+G37 -> 2704150.5 | H39: =H25+H37 -> 3119190.1 | I39: =I25+I37 -> 3534229.8 | ... Y39: =Y25+Y37 -> 10894865
A40: Renta provision (35% if positive) | B40: =-MAX(B39,0)*Assumptions!$B$23 -> -220133.24 | C40: =-MAX(C39,0)*Assumptions!$B$23 -> -365397.13 | D40: =-MAX(D39,0)*Assumptions!$B$23 -> -510661.01 | E40: =-MAX(E39,0)*Assumptions!$B$23 -> -655924.89 | F40: =-MAX(F39,0)*Assumptions!$B$23 -> -801188.78 | G40: =-MAX(G39,0)*Assumptions!$B$23 -> -946452.66 | H40: =-MAX(H39,0)*Assumptions!$B$23 -> -1091716.5 | I40: =-MAX(I39,0)*Assumptions!$B$23 -> -1236980.4 | ... Y40: =-MAX(Y39,0)*Assumptions!$B$23 -> -3813202.6
A41: Net profit | B41: =B39+B40 -> 408818.88 | C41: =C39+C40 -> 678594.66 | D41: =D39+D40 -> 948370.45 | E41: =E39+E40 -> 1218146.2 | F41: =F39+F40 -> 1487922 | G41: =G39+G40 -> 1757697.8 | H41: =H39+H40 -> 2027473.6 | I41: =I39+I40 -> 2297249.4 | ... Y41: =Y39+Y40 -> 7081661.9
A42: Cumulative net profit | B42: =B41 -> 408818.88 | C42: =B42+C41 -> 1087413.5 | D42: =C42+D41 -> 2035784 | E42: =D42+E41 -> 3253930.2 | F42: =E42+F41 -> 4741852.2 | G42: =F42+G41 -> 6499550 | H42: =G42+H41 -> 8527023.6 | I42: =H42+I41 -> 10824273 | J42: =I42+J41 -> 13391298 | ... Y42: =X42+Y41 -> 87311770

Sheet Unit Economics
A1: Per-customer Unit Economics (12-month view)
A3: Assumes: 1 page sale + 1 Plan de ventas customer, no churn, 12 months recurring.
A5: REVENUE
A6: Page revenue (gross, IVA incl) | B6: =Assumptions!$B$9 -> 400000
A7: MRR revenue × 12 months (gross) | B7: =Assumptions!$B$10*12 -> 1800000
A8: Total gross revenue per customer | B8: =B6+B7 -> 2200000
A9: Less: IVA payable | B9: =-B8*Assumptions!$B$11/(1+Assumptions!$B$11) -> -351260.5
A10: Net revenue per customer | B10: =B8+B9 -> 1848739.5
A12: VARIABLE COSTS
A13: Commission one-time (20% × page) | B13: =-B6*Assumptions!$B$13 -> -80000
A14: Commission recurring (10% × MRR × 12) | B14: =-B7*Assumptions!$B$14 -> -180000
A15: Wompi · page (1 transaction) | B15: =-(B6*Assumptions!$B$18+Assumptions!$B$19)*(1+Assumptions!$B$20) -> -15303.4
A16: Wompi · MRR (12 transactions) | B16: =-12*(Assumptions!$B$10*Assumptions!$B$18+Assumptions!$B$19)*(1+Assumptions!$B$20) -> -76897.8
A17: ICA on net revenue | B17: =-B10*Assumptions!$B$22 -> -12941.176
A18: Total variable cost per customer | B18: =SUM(B13:B17) -> -365142.38
A20: Contribution margin per customer | B20: =B10+B18 -> 1483597.1
A21: Contribution margin % | B21: =IFERROR(B20/B10,0) -> 0.80249117
A23: RAMP / SCALE
A24: 12-month contribution at base sales rate | B24: =B20*Assumptions!$B$5 -> 5934388.5 | C24: Per-customer contribution × monthly new customers
A25: Fixed costs total per month | B25: =-(Assumptions!$B$25+Assumptions!$B$26+Assumptions!$B$27+Assumptions!$B$28+Assumptions!$B$29+Assumptions!$B$32+Assumptions!$B$33+Assumptions!$B$34) -> -740000
A26: Fixed costs total per year | B26: =B25*12 -> -8880000
A27: Breakeven: new sales/mo at steady state | B27: =IFERROR(-B25*12/B20,0) -> 5.9854524 | C27: Sales/mo needed for one cohort's 12-mo contribution to cover annual fixed costs

Sheet Notes
A1: Notes & Assumptions
A4: PRICING ASSUMPTION: All customer-facing prices ($400.000 page, $150.000 MRR) are assumed to INCLUDE IVA.
A5: Net revenue to NSC = price / 1.19. If your published prices are pre-IVA (customer pays $400k + 19%), set the IVA rate to 0% in
A6: the Assumptions sheet to see top-line revenue at the headline price.
A8: COMMISSIONS: Per the signed contractor agreement: 20% one-time on the page sale, 10% recurring on each MRR payment for 12 months,
A9: paid 30 days after sale close (Clause 5 MBG clawback). The model expenses commissions in the month earned (accrual basis).
A11: RETEFUENTE: 10% withheld from contractor commission and remitted to DIAN. Neutral to NSC's P&L (you pay the contractor the same
A12: gross amount; the withholding flows through). Shown in Assumptions for reference only.
A14: SOCIAL SECURITY (PILA): The contractor pays his own salud + pensión + ARL. Contract clause 6 requires monthly PILA receipt before
A15: commission payment. No direct cost to NSC, but failure to verify creates joint-liability exposure. NOT modeled as an expense.
A17: WOMPI: Modeled at 2.99% + $900 per transaction + 19% IVA on the fee. Colombia card rate. PSE is cheaper (~1.79%).
A18: If most customers pay by PSE, lower the % in Assumptions.
... A40: relying on these numbers for tax declarations.
